pylaptoppred/__init__.py
pylaptoppred/copy_file.py
pylaptoppred/function_data_cleaning.py
pylaptoppred/model.py
pylaptoppred/save_plot.py
pylaptoppred-0.1.0.dist-info/LICENSE
pylaptoppred-0.1.0.dist-info/METADATA
pylaptoppred-0.1.0.dist-info/WHEEL
pylaptoppred-0.1.0.dist-info/RECORD
